Workbook

Sheet Dashboard
B2: Supplier Management Dashboard
B3: ="As of "&TEXT(TODAY(),"DD MMMM YYYY")&" · Sources: GL Listing · VENDMAST · Retail Budget"
B6: Total Outstanding | D6: Overdue Amount | F6: Overdue Invoices | H6: On-Time Payment
B7: =SUMIF(GL_Data[Status],"<>Paid",GL_Data[Amount (EUR)]) | D7: =SUMIF(GL_Data[Status],"Overdue",GL_Data[Amount (EUR)]) | F7: =COUNTIF(GL_Data[Status],"Overdue") | H7: =IFERROR(COUNTIF(GL_Data[Status],"Paid")/COUNTA(GL_Data[Status]),0)
B8: =COUNTIF(GL_Data[Status],"<>Paid")&" open invoices" | D8: =COUNTIF(GL_Data[Status],"Overdue")&" invoices past due" | F8: ="out of "&COUNTA(GL_Data[Status])&" total invoices" | H8: =COUNTIF(GL_Data[Status],"Paid")&" invoices paid on time"
B13: Top 5 Overdue Suppliers | F13: Monthly Invoiced Amount Trend
B36: Overdue Invoice Detail (sorted by days overdue — requires Excel 365)
B37: Supplier | C37: Category | D37: Invoice Date | E37: Due Date | F37: Days Past Due | G37: Amount (EUR) | H37: Status
B38: =IFERROR(_Calc!$A$15,"") | C38: =IFERROR(_Calc!$B$15,"") | D38: =IFERROR(_Calc!$C$15,"") | E38: =IFERROR(_Calc!$D$15,"") | F38: =IFERROR(_Calc!$E$15,"") | G38: =IFERROR(_Calc!$F$15,"") | H38: =IFERROR(_Calc!$G$15,"")
B39: =IFERROR(_Calc!$A$16,"") | C39: =IFERROR(_Calc!$B$16,"") | D39: =IFERROR(_Calc!$C$16,"") | E39: =IFERROR(_Calc!$D$16,"") | F39: =IFERROR(_Calc!$E$16,"") | G39: =IFERROR(_Calc!$F$16,"") | H39: =IFERROR(_Calc!$G$16,"")
B40: =IFERROR(_Calc!$A$17,"") | C40: =IFERROR(_Calc!$B$17,"") | D40: =IFERROR(_Calc!$C$17,"") | E40: =IFERROR(_Calc!$D$17,"") | F40: =IFERROR(_Calc!$E$17,"") | G40: =IFERROR(_Calc!$F$17,"") | H40: =IFERROR(_Calc!$G$17,"")
B41: =IFERROR(_Calc!$A$18,"") | C41: =IFERROR(_Calc!$B$18,"") | D41: =IFERROR(_Calc!$C$18,"") | E41: =IFERROR(_Calc!$D$18,"") | F41: =IFERROR(_Calc!$E$18,"") | G41: =IFERROR(_Calc!$F$18,"") | H41: =IFERROR(_Calc!$G$18,"")
B42: =IFERROR(_Calc!$A$19,"") | C42: =IFERROR(_Calc!$B$19,"") | D42: =IFERROR(_Calc!$C$19,"") | E42: =IFERROR(_Calc!$D$19,"") | F42: =IFERROR(_Calc!$E$19,"") | G42: =IFERROR(_Calc!$F$19,"") | H42: =IFERROR(_Calc!$G$19,"")
B43: =IFERROR(_Calc!$A$20,"") | C43: =IFERROR(_Calc!$B$20,"") | D43: =IFERROR(_Calc!$C$20,"") | E43: =IFERROR(_Calc!$D$20,"") | F43: =IFERROR(_Calc!$E$20,"") | G43: =IFERROR(_Calc!$F$20,"") | H43: =IFERROR(_Calc!$G$20,"")
B44: =IFERROR(_Calc!$A$21,"") | C44: =IFERROR(_Calc!$B$21,"") | D44: =IFERROR(_Calc!$C$21,"") | E44: =IFERROR(_Calc!$D$21,"") | F44: =IFERROR(_Calc!$E$21,"") | G44: =IFERROR(_Calc!$F$21,"") | H44: =IFERROR(_Calc!$G$21,"")
B45: =IFERROR(_Calc!$A$22,"") | C45: =IFERROR(_Calc!$B$22,"") | D45: =IFERROR(_Calc!$C$22,"") | E45: =IFERROR(_Calc!$D$22,"") | F45: =IFERROR(_Calc!$E$22,"") | G45: =IFERROR(_Calc!$F$22,"") | H45: =IFERROR(_Calc!$G$22,"")
B46: =IFERROR(_Calc!$A$23,"") | C46: =IFERROR(_Calc!$B$23,"") | D46: =IFERROR(_Calc!$C$23,"") | E46: =IFERROR(_Calc!$D$23,"") | F46: =IFERROR(_Calc!$E$23,"") | G46: =IFERROR(_Calc!$F$23,"") | H46: =IFERROR(_Calc!$G$23,"")
B47: =IFERROR(_Calc!$A$24,"") | C47: =IFERROR(_Calc!$B$24,"") | D47: =IFERROR(_Calc!$C$24,"") | E47: =IFERROR(_Calc!$D$24,"") | F47: =IFERROR(_Calc!$E$24,"") | G47: =IFERROR(_Calc!$F$24,"") | H47: =IFERROR(_Calc!$G$24,"")
B48: =IFERROR(_Calc!$A$25,"") | C48: =IFERROR(_Calc!$B$25,"") | D48: =IFERROR(_Calc!$C$25,"") | E48: =IFERROR(_Calc!$D$25,"") | F48: =IFERROR(_Calc!$E$25,"") | G48: =IFERROR(_Calc!$F$25,"") | H48: =IFERROR(_Calc!$G$25,"")
B49: =IFERROR(_Calc!$A$26,"") | C49: =IFERROR(_Calc!$B$26,"") | D49: =IFERROR(_Calc!$C$26,"") | E49: =IFERROR(_Calc!$D$26,"") | F49: =IFERROR(_Calc!$E$26,"") | G49: =IFERROR(_Calc!$F$26,"") | H49: =IFERROR(_Calc!$G$26,"")
B50: =IFERROR(_Calc!$A$27,"") | C50: =IFERROR(_Calc!$B$27,"") | D50: =IFERROR(_Calc!$C$27,"") | E50: =IFERROR(_Calc!$D$27,"") | F50: =IFERROR(_Calc!$E$27,"") | G50: =IFERROR(_Calc!$F$27,"") | H50: =IFERROR(_Calc!$G$27,"")
B51: =IFERROR(_Calc!$A$28,"") | C51: =IFERROR(_Calc!$B$28,"") | D51: =IFERROR(_Calc!$C$28,"") | E51: =IFERROR(_Calc!$D$28,"") | F51: =IFERROR(_Calc!$E$28,"") | G51: =IFERROR(_Calc!$F$28,"") | H51: =IFERROR(_Calc!$G$28,"")
B52: =IFERROR(_Calc!$A$29,"") | C52: =IFERROR(_Calc!$B$29,"") | D52: =IFERROR(_Calc!$C$29,"") | E52: =IFERROR(_Calc!$D$29,"") | F52: =IFERROR(_Calc!$E$29,"") | G52: =IFERROR(_Calc!$F$29,"") | H52: =IFERROR(_Calc!$G$29,"")
B53: =IFERROR(_Calc!$A$30,"") | C53: =IFERROR(_Calc!$B$30,"") | D53: =IFERROR(_Calc!$C$30,"") | E53: =IFERROR(_Calc!$D$30,"") | F53: =IFERROR(_Calc!$E$30,"") | G53: =IFERROR(_Calc!$F$30,"") | H53: =IFERROR(_Calc!$G$30,"")
B54: =IFERROR(_Calc!$A$31,"") | C54: =IFERROR(_Calc!$B$31,"") | D54: =IFERROR(_Calc!$C$31,"") | E54: =IFERROR(_Calc!$D$31,"") | F54: =IFERROR(_Calc!$E$31,"") | G54: =IFERROR(_Calc!$F$31,"") | H54: =IFERROR(_Calc!$G$31,"")
B55: =IFERROR(_Calc!$A$32,"") | C55: =IFERROR(_Calc!$B$32,"") | D55: =IFERROR(_Calc!$C$32,"") | E55: =IFERROR(_Calc!$D$32,"") | F55: =IFERROR(_Calc!$E$32,"") | G55: =IFERROR(_Calc!$F$32,"") | H55: =IFERROR(_Calc!$G$32,"")
B56: =IFERROR(_Calc!$A$33,"") | C56: =IFERROR(_Calc!$B$33,"") | D56: =IFERROR(_Calc!$C$33,"") | E56: =IFERROR(_Calc!$D$33,"") | F56: =IFERROR(_Calc!$E$33,"") | G56: =IFERROR(_Calc!$F$33,"") | H56: =IFERROR(_Calc!$G$33,"")
B57: =IFERROR(_Calc!$A$34,"") | C57: =IFERROR(_Calc!$B$34,"") | D57: =IFERROR(_Calc!$C$34,"") | E57: =IFERROR(_Calc!$D$34,"") | F57: =IFERROR(_Calc!$E$34,"") | G57: =IFERROR(_Calc!$F$34,"") | H57: =IFERROR(_Calc!$G$34,"")
B59: =COUNTIF(GL_Data[Status],"Overdue")&" overdue | "&COUNTIF(GL_Data[Status],"Open")&" open | "&COUNTIF(GL_Data[Status],"Paid")&" paid" | E59: ="Total budget: EUR "&TEXT(SUM(Retail_Data[Budget (EUR)]),"#,##0")&" | AP open: EUR "&TEXT(SUM(VENDMAST_Data[AP Balance (EUR)]),"#,##0")

Sheet GL_Listing
A1: Journal Description | B1: Supplier Code | C1: Supplier Name | D1: Amount (EUR) | E1: Currency | F1: Invoice Date | G1: Due Date | H1: Category | I1: GL Code | J1: PO Number | K1: Status | L1: Days Past Due
A2: Acme Logistics BV | B2: SUP001 | C2: Acme Logistics BV | D2: 12152.8 | E2: EUR | F2: 46046 | G2: 46079 | H2: IT | I2: 6200 | J2: PO-2026-1000 | K2: Overdue | L2: =IF([@Status]<>"Paid",MAX(0,TODAY()-[@[Due Date]]),0)
A3: Acme Logistics BV | B3: SUP001 | C3: Acme Logistics BV | D3: 27186.42 | E3: EUR | F3: 46077 | G3: 46104 | H3: IT | I3: 6200 | J3: PO-2026-1001 | K3: Overdue | L3: =IF([@Status]<>"Paid",MAX(0,TODAY()-[@[Due Date]]),0)
A4: Acme Logistics BV | B4: SUP001 | C4: Acme Logistics BV | D4: 23482.96 | E4: EUR | F4: 46060 | G4: 46092 | H4: IT | I4: 6200 | J4: PO-2026-1002 | K4: Overdue | L4: =IF([@Status]<>"Paid",MAX(0,TODAY()-[@[Due Date]]),0)
A5: Acme Logistics BV | B5: SUP001 | C5: Acme Logistics BV | D5: 11089.17 | E5: EUR | F5: 46076 | G5: 46114 | H5: IT | I5: 6200 | J5: PO-2026-1003 | K5: Paid | L5: =IF([@Status]<>"Paid",MAX(0,TODAY()-[@[Due Date]]),0)
A6: PO-2026-1004 | B6: SUP001 | C6: Acme Logistics BV | D6: 16300.9 | E6: EUR | F6: 46104 | G6: 46142 | H6: IT | I6: 6200 | J6: PO-2026-1004 | K6: Overdue | L6: =IF([@Status]<>"Paid",MAX(0,TODAY()-[@[Due Date]]),0)
A7: PO-2026-1005 | B7: SUP001 | C7: Acme Logistics BV | D7: 5707.16 | E7: EUR | F7: 46115 | G7: 46152 | H7: IT | I7: 6200 | J7: PO-2026-1005 | K7: Paid | L7: =IF([@Status]<>"Paid",MAX(0,TODAY()-[@[Due Date]]),0)
A8: PO-2026-1006 | B8: SUP001 | C8: Acme Logistics BV | D8: 24825.92 | E8: EUR | F8: 46166 | G8: 46205 | H8: IT | I8: 6200 | J8: PO-2026-1006 | K8: Paid | L8: =IF([@Status]<>"Paid",MAX(0,TODAY()-[@[Due Date]]),0)
A9: PO-2026-1007 | B9: SUP001 | C9: Acme Logistics BV | D9: 37579.1 | E9: EUR | F9: 46191 | G9: 46225 | H9: IT | I9: 6200 | J9: PO-2026-1007 | K9: Paid | L9: =IF([@Status]<>"Paid",MAX(0,TODAY()-[@[Due Date]]),0)
A10: Acme Logistics BV | B10: SUP001 | C10: Acme Logistics BV | D10: 3493.36 | E10: EUR | F10: 46210 | G10: 46237 | H10: IT | I10: 6200 | J10: PO-2026-1008 | K10: Open | L10: =IF([@Status]<>"Paid",MAX(0,TODAY()-[@[Due Date]]),0)
A11: Acme Logistics BV | B11: SUP001 | C11: Acme Logistics BV | D11: 44357.14 | E11: EUR | F11: 46228 | G11: 46262 | H11: IT | I11: 6200 | J11: PO-2026-1009 | K11: Open | L11: =IF([@Status]<>"Paid",MAX(0,TODAY()-[@[Due Date]]),0)
A12: PO-2026-1010 | B12: SUP001 | C12: Acme Logistics BV | D12: 18035.49 | E12: EUR | F12: 46231 | G12: 46259 | H12: IT | I12: 6200 | J12: PO-2026-1010 | K12: Open | L12: =IF([@Status]<>"Paid",MAX(0,TODAY()-[@[Due Date]]),0)
A13: TechParts Solutions | B13: SUP002 | C13: TechParts Solutions | D13: 10613.56 | E13: EUR | F13: 46034 | G13: 46085 | H13: Marketing | I13: 6600 | J13: PO-2026-1011 | K13: Overdue | L13: =IF([@Status]<>"Paid",MAX(0,TODAY()-[@[Due Date]]),0)
... A134: PO-2026-1132 | B134: SUP010 | C134: HR Partners BV | D134: 13527.73 | E134: EUR | F134: 46210 | G134: 46250 | H134: Marketing | I134: 6600 | J134: PO-2026-1132 | K134: Open | L134: =IF([@Status]<>"Paid",MAX(0,TODAY()-[@[Due Date]]),0)

Sheet VENDMAST
A1: Supplier Code | B1: Supplier Name | C1: AP Balance (EUR) | D1: Currency | E1: Payment Method | F1: Payment Terms (days)
A2: SUP001 | B2: Acme Logistics BV | C2: 145009.07 | D2: EUR | E2: Bank Transfer | F2: 30
A3: SUP002 | B3: TechParts Solutions | C3: 181148.29 | D3: EUR | E3: Bank Transfer | F3: 45
A4: SUP003 | B4: Global Freight NL | C4: 217664.3 | D4: EUR | E4: SEPA | F4: 30
A5: SUP004 | B5: OfficePlus Nederland | C5: 144251.31 | D5: EUR | E5: Bank Transfer | F5: 60
A6: SUP005 | B6: CleanServ BV | C6: 148227.66 | D6: EUR | E6: Direct Debit | F6: 30
A7: SUP006 | B7: ITware Group | C7: 198478.61 | D7: EUR | E7: Bank Transfer | F7: 30
A8: SUP007 | B8: Alpha Consulting | C8: 184815.6 | D8: EUR | E8: Bank Transfer | F8: 45
A9: SUP008 | B9: Prime Maintenance Co | C9: 214961.62 | D9: EUR | E9: SEPA | F9: 30
A10: SUP009 | B10: Retail Display Systems | C10: 166830.99 | D10: EUR | E10: Bank Transfer | F10: 60
A11: SUP010 | B11: HR Partners BV | C11: 287363.1 | D11: EUR | E11: Bank Transfer | F11: 30

Sheet Retail_Team
A1: Period | B1: Supplier Name | C1: Category | D1: GL Code | E1: PO Number | F1: Budget (EUR)
A2: 2026-01 | B2: Acme Logistics BV | C2: IT | D2: 6200 | E2: PO-2026-4180 | F2: 58512.04
A3: 2026-02 | B3: Acme Logistics BV | C3: IT | D3: 6200 | E3: PO-2026-6912 | F3: 43327.4
A4: 2026-03 | B4: Acme Logistics BV | C4: IT | D4: 6200 | E4: PO-2026-1231 | F4: 112042.4
A5: 2026-04 | B5: Acme Logistics BV | C5: IT | D5: 6200 | E5: PO-2026-3073 | F5: 55660.47
A6: 2026-05 | B6: Acme Logistics BV | C6: IT | D6: 6200 | E6: PO-2026-1893 | F6: 91936.67
A7: 2026-06 | B7: Acme Logistics BV | C7: IT | D7: 6200 | E7: PO-2026-3068 | F7: 102923.06
A8: 2026-07 | B8: Acme Logistics BV | C8: IT | D8: 6200 | E8: PO-2026-9042 | F8: 33336.39
A9: 2026-01 | B9: TechParts Solutions | C9: Logistics | D9: 6100 | E9: PO-2026-5658 | F9: 81021.6
A10: 2026-02 | B10: TechParts Solutions | C10: Logistics | D10: 6100 | E10: PO-2026-8216 | F10: 64291.77
A11: 2026-03 | B11: TechParts Solutions | C11: Logistics | D11: 6100 | E11: PO-2026-1841 | F11: 52822.19
A12: 2026-04 | B12: TechParts Solutions | C12: Logistics | D12: 6100 | E12: PO-2026-8827 | F12: 34831.33
A13: 2026-05 | B13: TechParts Solutions | C13: Logistics | D13: 6100 | E13: PO-2026-2070 | F13: 72091.97
... A71: 2026-07 | B71: HR Partners BV | C71: Maintenance | D71: 6800 | E71: PO-2026-6091 | F71: 91609.07

Sheet _Calc
A1: Supplier | B1: Overdue (EUR) | D1: Supplier | E1: Overdue (EUR) | G1: Month | H1: Invoiced (EUR)
A2: =IFERROR(INDEX(VENDMAST_Data[Supplier Name],1),"") | B2: =IF(A2="","",SUMIFS(GL_Data[Amount (EUR)],GL_Data[Supplier Name],A2,GL_Data[Status],"Overdue")) | D2: =IFERROR(INDEX($A$2:$A$11,MATCH(LARGE($B$2:$B$11,1),$B$2:$B$11,0)),"") | E2: =IFERROR(LARGE($B$2:$B$11,1),0) | G2: =DATE(2026,1,1) | H2: =SUMPRODUCT((YEAR(GL_Data[Invoice Date])=YEAR(G2))*(MONTH(GL_Data[Invoice Date])=MONTH(G2))*GL_Data[Amount (EUR)])
A3: =IFERROR(INDEX(VENDMAST_Data[Supplier Name],2),"") | B3: =IF(A3="","",SUMIFS(GL_Data[Amount (EUR)],GL_Data[Supplier Name],A3,GL_Data[Status],"Overdue")) | D3: =IFERROR(INDEX($A$2:$A$11,MATCH(LARGE($B$2:$B$11,2),$B$2:$B$11,0)),"") | E3: =IFERROR(LARGE($B$2:$B$11,2),0) | G3: =EDATE(G2,1) | H3: =SUMPRODUCT((YEAR(GL_Data[Invoice Date])=YEAR(G3))*(MONTH(GL_Data[Invoice Date])=MONTH(G3))*GL_Data[Amount (EUR)])
A4: =IFERROR(INDEX(VENDMAST_Data[Supplier Name],3),"") | B4: =IF(A4="","",SUMIFS(GL_Data[Amount (EUR)],GL_Data[Supplier Name],A4,GL_Data[Status],"Overdue")) | D4: =IFERROR(INDEX($A$2:$A$11,MATCH(LARGE($B$2:$B$11,3),$B$2:$B$11,0)),"") | E4: =IFERROR(LARGE($B$2:$B$11,3),0) | G4: =EDATE(G3,1) | H4: =SUMPRODUCT((YEAR(GL_Data[Invoice Date])=YEAR(G4))*(MONTH(GL_Data[Invoice Date])=MONTH(G4))*GL_Data[Amount (EUR)])
A5: =IFERROR(INDEX(VENDMAST_Data[Supplier Name],4),"") | B5: =IF(A5="","",SUMIFS(GL_Data[Amount (EUR)],GL_Data[Supplier Name],A5,GL_Data[Status],"Overdue")) | D5: =IFERROR(INDEX($A$2:$A$11,MATCH(LARGE($B$2:$B$11,4),$B$2:$B$11,0)),"") | E5: =IFERROR(LARGE($B$2:$B$11,4),0) | G5: =EDATE(G4,1) | H5: =SUMPRODUCT((YEAR(GL_Data[Invoice Date])=YEAR(G5))*(MONTH(GL_Data[Invoice Date])=MONTH(G5))*GL_Data[Amount (EUR)])
A6: =IFERROR(INDEX(VENDMAST_Data[Supplier Name],5),"") | B6: =IF(A6="","",SUMIFS(GL_Data[Amount (EUR)],GL_Data[Supplier Name],A6,GL_Data[Status],"Overdue")) | D6: =IFERROR(INDEX($A$2:$A$11,MATCH(LARGE($B$2:$B$11,5),$B$2:$B$11,0)),"") | E6: =IFERROR(LARGE($B$2:$B$11,5),0) | G6: =EDATE(G5,1) | H6: =SUMPRODUCT((YEAR(GL_Data[Invoice Date])=YEAR(G6))*(MONTH(GL_Data[Invoice Date])=MONTH(G6))*GL_Data[Amount (EUR)])
A7: =IFERROR(INDEX(VENDMAST_Data[Supplier Name],6),"") | B7: =IF(A7="","",SUMIFS(GL_Data[Amount (EUR)],GL_Data[Supplier Name],A7,GL_Data[Status],"Overdue")) | G7: =EDATE(G6,1) | H7: =SUMPRODUCT((YEAR(GL_Data[Invoice Date])=YEAR(G7))*(MONTH(GL_Data[Invoice Date])=MONTH(G7))*GL_Data[Amount (EUR)])
A8: =IFERROR(INDEX(VENDMAST_Data[Supplier Name],7),"") | B8: =IF(A8="","",SUMIFS(GL_Data[Amount (EUR)],GL_Data[Supplier Name],A8,GL_Data[Status],"Overdue")) | G8: =EDATE(G7,1) | H8: =SUMPRODUCT((YEAR(GL_Data[Invoice Date])=YEAR(G8))*(MONTH(GL_Data[Invoice Date])=MONTH(G8))*GL_Data[Amount (EUR)])
A9: =IFERROR(INDEX(VENDMAST_Data[Supplier Name],8),"") | B9: =IF(A9="","",SUMIFS(GL_Data[Amount (EUR)],GL_Data[Supplier Name],A9,GL_Data[Status],"Overdue"))
A10: =IFERROR(INDEX(VENDMAST_Data[Supplier Name],9),"") | B10: =IF(A10="","",SUMIFS(GL_Data[Amount (EUR)],GL_Data[Supplier Name],A10,GL_Data[Status],"Overdue"))
A11: =IFERROR(INDEX(VENDMAST_Data[Supplier Name],10),"") | B11: =IF(A11="","",SUMIFS(GL_Data[Amount (EUR)],GL_Data[Supplier Name],A11,GL_Data[Status],"Overdue"))
A15: =SORT(FILTER(CHOOSE({1,2,3,4,5,6,7},GL_Data[Supplier Name],GL_Data[Category],GL_Data[Invoice Date],GL_Data[Due Date],GL_Data[Days Past Due],GL_Data[Amount (EUR)],GL_Data[Status]),GL_Data[Status]="Overdue"),5,-1)
